{
  "id": "1394b3f2-282f-4f59-9501-f93d50e926d5",
  "prevId": "00000000-0000-0000-0000-000000000000",
  "version": "7",
  "dialect": "postgresql",
  "tables": {
    "public.user": {
      "name": "user",
      "schema": "",
      "columns": {
        "userId": {
          "name": "userId",
          "type": "varchar",
          "primaryKey": true,
          "notNull": true
        },
        "username": {
          "name": "username",
          "type": "varchar",
          "primaryKey": false,
          "notNull": true
        },
        "email": {
          "name": "email",
          "type": "varchar",
          "primaryKey": false,
          "notNull": true
        },
        "avatar": {
          "name": "avatar",
          "type": "varchar",
          "primaryKey": false,
          "notNull": false,
          "default": "''"
        },
        "createdAt": {
          "name": "createdAt",
          "type": "timestamp",
          "primaryKey": false,
          "notNull": true,
          "default": "now()"
        }
      },
      "indexes": {},
      "foreignKeys": {},
      "compositePrimaryKeys": {},
      "uniqueConstraints": {},
      "checkConstraints": {}
    }
  },
  "enums": {},
  "schemas": {},
  "sequences": {},
  "views": {},
  "_meta": {
    "columns": {},
    "schemas": {},
    "tables": {}
  }
}